shiny_semantic/__init__.py
shiny_semantic/_utils.py
shiny_semantic/page.py
shiny_semantic/collections/__init__.py
shiny_semantic/elements/__init__.py
shiny_semantic/elements/button.py
shiny_semantic/elements/container.py
shiny_semantic/elements/divider.py
shiny_semantic/elements/emoji.py
shiny_semantic/elements/flag.py
shiny_semantic/elements/header.py
shiny_semantic/elements/icon.py
shiny_semantic/elements/input.py
shiny_semantic/elements/segment.py
shiny_semantic/modules/__init__.py
shiny_semantic/modules/checkbox.py
shiny_semantic/modules/dropdown.py
shiny_semantic/modules/modal.py
shiny_semantic/modules/slider.py
shiny_semantic/types/__init__.py
shiny_semantic/views/__init__.py
shiny_semantic/views/statistic.py
shiny_semantic/www/.DS_Store
shiny_semantic/www/shiny-semantic-bindings.js
shiny_semantic/www/bindings/semanticButton.js
shiny_semantic/www/bindings/semanticCheckbox.js
shiny_semantic/www/bindings/semanticCheckboxGroup.js
shiny_semantic/www/bindings/semanticDropdown.js
shiny_semantic/www/bindings/semanticModal.js
shiny_semantic/www/bindings/semanticSlider.js
shiny_semantic/www/semantic/fomantic.min.css
shiny_semantic/www/semantic/fomantic.min.js
shiny_semantic/www/semantic/themes/default/assets/fonts/Lato-Bold.woff
shiny_semantic/www/semantic/themes/default/assets/fonts/Lato-Bold.woff2
shiny_semantic/www/semantic/themes/default/assets/fonts/Lato-BoldItalic.woff
shiny_semantic/www/semantic/themes/default/assets/fonts/Lato-BoldItalic.woff2
shiny_semantic/www/semantic/themes/default/assets/fonts/Lato-Italic.woff
shiny_semantic/www/semantic/themes/default/assets/fonts/Lato-Italic.woff2
shiny_semantic/www/semantic/themes/default/assets/fonts/Lato-Regular.woff
shiny_semantic/www/semantic/themes/default/assets/fonts/Lato-Regular.woff2
shiny_semantic/www/semantic/themes/default/assets/fonts/LatoLatin-Bold.woff
shiny_semantic/www/semantic/themes/default/assets/fonts/LatoLatin-Bold.woff2
shiny_semantic-0.1.3.dist-info/LICENSE
shiny_semantic-0.1.3.dist-info/METADATA
shiny_semantic-0.1.3.dist-info/WHEEL
shiny_semantic-0.1.3.dist-info/top_level.txt
shiny_semantic-0.1.3.dist-info/RECORD
