Metadata-Version: 2.1
Name: shiny-semantic
Version: 0.1.3
Summary: Semantic UI components in Shiny for Python
Author-email: Pavel Demin <pavel.demin@appsilon.com>, Kamil Żyła <kamil@appsilon.com>
Maintainer-email: Appsilon <opensource@appsilon.com>
License: GNU LESSER GENERAL PUBLIC LICENSE
Project-URL: GitHub, https://github.com/Appsilon/py_shiny_semantic
Keywords: shiny,semantic,web
Classifier: Programming Language :: Python :: 3
Requires-Python: >=3.10
License-File: LICENSE
Requires-Dist: shiny (>=0.2.9)
Provides-Extra: dev
Requires-Dist: black ; extra == 'dev'
Requires-Dist: isort ; extra == 'dev'
Requires-Dist: flake8 ; extra == 'dev'
Requires-Dist: pre-commit ; extra == 'dev'
Requires-Dist: bumpver ; extra == 'dev'
